[ "java.util.ArrayList", [ [ "grid.Tile", {
  "myData" : [ "java.util.HashMap", { } ],
  "neededData" : [ "java.util.ArrayList", [ ] ],
  "myImagePath" : "resources/grass.png",
  "moveCost" : 1,
  "statMods" : [ "java.util.HashMap", { } ],
  "neighbors" : null,
  "coordinate" : null,
  "distanceToGoal" : 0,
  "parent" : null,
  "length" : 0,
  "active" : false,
  "image" : null,
  "passableList" : [ "java.util.ArrayList", [ "everything" ] ],
  "interaction" : null,
  "imagePath" : "resources/grass.png",
  "name" : "grass"
} ], [ "grid.Tile", {
  "myData" : [ "java.util.HashMap", { } ],
  "neededData" : [ "java.util.ArrayList", [ ] ],
  "myImagePath" : "resources/water.png",
  "moveCost" : 2,
  "statMods" : [ "java.util.HashMap", { } ],
  "neighbors" : null,
  "coordinate" : null,
  "distanceToGoal" : 0,
  "parent" : null,
  "length" : 0,
  "active" : false,
  "image" : null,
  "passableList" : [ "java.util.ArrayList", [ "everything" ] ],
  "interaction" : null,
  "imagePath" : "resources/water.png",
  "name" : "water"
} ] ] ]